{
    "namespace": "NCFGroup\\Protos\\FundGate",
    "comment": "获取公募基金净值历史数据",
    "author": "fupingzhou",
    "use": {
        "0": "NCFGroup\\Common\\Extensions\\Base\\AbstractRequestBase"
    },
    "extend": "AbstractRequestBase",
    "properties": {
        "0": {
            "required": true,
            "name": "fundCode",
            "type": "string",
            "comment": "基金代码"
        },
        "1": {
            "required": true,
            "name": "startDay",
            "type": "string",
            "comment": "起始日期"
        },
        "2": {
            "required": true,
            "name": "endDay",
            "type": "string",
            "comment": "截止日期"
        },
        "3": {
            "required": false,
            "name": "sort",
            "type": "string",
            "comment": "排序方式",
            "default": "asc"
        },
        "4": {
            "required": false,
            "name": "pageNo",
            "type": "int",
            "comment": "页码",
            "default": 0
        },
        "5": {
            "required": false,
            "name": "pageSize",
            "type": "int",
            "comment": "每页记录数",
            "default": 0
        }
    }
}