{
    "namespace": "NCFGroup\\Protos\\Future",
    "comment": "获取配资方案列表",
    "author": "guweigang",
    "use": {
        "0": "NCFGroup\\Common\\Extensions\\Base\\AbstractRequestBase",
        "1": "NCFGroup\\Protos\\Future\\Enum\\OrderType"
    },
    "extend": "AbstractRequestBase",
    "properties": {
        "0": {
            "required": true,
            "name": "orderType",
            "type": "OrderType",
            "comment": "配资类型: 天/月"
        },
        "1": {
            "required": false,
            "name": "amount",
            "type": "int",
            "comment": "保证金额（分）",
            "default": 0
        },
        "2": {
            "required": false,
            "name": "month",
            "type": "int",
            "comment": "配资周期",
            "default": 1
        }
    }
}
